README.md
setup.py
Image/Image.py
Image/__init__.py
pypixel.egg-info/PKG-INFO
pypixel.egg-info/SOURCES.txt
pypixel.egg-info/dependency_links.txt
pypixel.egg-info/top_level.txt