Metadata-Version: 2.1
Name: pypixel
Version: 0.1.7
Summary: A Image Processing Library
Home-page: https://github.com/JiaCheng-Huang/pypixel
Author: Jiacheng Huang
Author-email: Dylan.JiaCheng.Huang@outlook.com
License: MIT
Platform: UNKNOWN
Classifier: Topic :: Software Development :: Libraries :: Python Modules
Classifier: Programming Language :: Python
Classifier: Programming Language :: Python :: 3
